libclsprot/__init__.py
libclsprot/chipless.cp36-win32.pyd
libclsprot/libhxbuffer.dll
libclsprot/test.py
libclsprot-2.5.dist-info/LICENSE
libclsprot-2.5.dist-info/METADATA
libclsprot-2.5.dist-info/WHEEL
libclsprot-2.5.dist-info/top_level.txt
libclsprot-2.5.dist-info/RECORD
