Metadata-Version: 2.1
Name: libclsprot
Version: 2.5
Summary: Library for chipless Reader
Home-page: UNKNOWN
Author: Heyn
Author-email: heyunhuan@gmail.com
License: GPLv3
Keywords: chipless,hexin
Platform: any
Classifier: Development Status :: 3 - Alpha
Classifier: Intended Audience :: Developers
Classifier: Topic :: Software Development :: Build Tools
Classifier: License :: OSI Approved :: MIT License
Classifier: Programming Language :: Python :: 3
Classifier: Programming Language :: Python :: 3.6
Classifier: Programming Language :: Python :: Implementation :: CPython
Classifier: Programming Language :: Python :: Implementation :: PyPy
Requires-Dist: pyserial (>=3.4)
